README.md
setup.py
src/nr/__init__.py
src/nr.databind.egg-info/PKG-INFO
src/nr.databind.egg-info/SOURCES.txt
src/nr.databind.egg-info/dependency_links.txt
src/nr.databind.egg-info/entry_points.txt
src/nr.databind.egg-info/requires.txt
src/nr.databind.egg-info/top_level.txt
src/nr/databind/__init__.py
src/nr/databind/json.py
src/nr/databind/contrib/__init__.py
src/nr/databind/contrib/preprocessor.py
src/nr/databind/contrib/yaml.py
src/nr/databind/contrib/mixins/__init__.py
src/nr/databind/contrib/mixins/asdict.py
src/nr/databind/contrib/mixins/tuple.py
src/nr/databind/core/__init__.py
src/nr/databind/core/collection.py
src/nr/databind/core/datatypes.py
src/nr/databind/core/decoration.py
src/nr/databind/core/errors.py
src/nr/databind/core/interfaces.py
src/nr/databind/core/location.py
src/nr/databind/core/mapper.py
src/nr/databind/core/struct.py
src/nr/databind/core/union.py
src/nr/databind/util/__init__.py
src/nr/databind/util/typing.py