Metadata-Version: 2.1
Name: nr.databind
Version: 0.0.4
Summary: Bind structured data directly to typed objects.
Home-page: https://git.niklasrosenstein.com/NiklasRosenstein/nr-python-libs
Author: Niklas Rosenstein
Author-email: rosensteinniklas@gmail.com
License: MIT
Platform: UNKNOWN
Provides-Extra: test
